dloud_ads/__init__.py
dloud_ads/array_queue.py
dloud_ads/array_stack.py
dloud_ads/binary_tree.py
dloud_ads/circular_queue.py
dloud_ads/doubly_linked_base.py
dloud_ads/linked_binary_tree.py
dloud_ads/linked_deque.py
dloud_ads/linked_queue.py
dloud_ads/linked_stack.py
dloud_ads/positional_list.py
dloud_ads/tree.py
dloud_ads-0.0.2.dist-info/DESCRIPTION.rst
dloud_ads-0.0.2.dist-info/METADATA
dloud_ads-0.0.2.dist-info/RECORD
dloud_ads-0.0.2.dist-info/WHEEL
dloud_ads-0.0.2.dist-info/metadata.json
dloud_ads-0.0.2.dist-info/top_level.txt
tests/__init__.py
tests/test_array_queue.py
tests/test_array_stack.py
tests/test_circular_queue.py
tests/test_doubly_linked_base.py
tests/test_linked_deque.py
tests/test_linked_queue.py
tests/test_linked_stack.py
tests/test_positional_list.py
