Metadata-Version: 2.0
Name: dloud-ads
Version: 0.0.2
Summary: Abstract Data Structures commonly used in CS scenarios. Implemented by Data Loud Labs!
Home-page: https://github.com/dataloudlabs/dloud-ads
Author: Pedro Sousa
Author-email: pjgs.sousa@gmail.com
License: UNKNOWN
Platform: UNKNOWN
Classifier: Development Status :: 2 - Pre-Alpha
Classifier: Programming Language :: Python
Classifier: Programming Language :: Python :: 2
Classifier: Programming Language :: Python :: 2.7
Classifier: Programming Language :: Python :: 3
Classifier: Programming Language :: Python :: 3.4
Classifier: Programming Language :: Python :: 3.5
